vasim/__init__.py
vasim/commons/__init__.py
vasim/commons/utils.py
vasim/recommender/DummyAdditiveRecommender.py
vasim/recommender/DummyMultiplierRecommender.py
vasim/recommender/Recommender.py
vasim/recommender/__init__.py
vasim/recommender/cluster_state_provider/ClusterStateConfig.py
vasim/recommender/cluster_state_provider/ClusterStateProvider.py
vasim/recommender/cluster_state_provider/ConfigStateConstants.py
vasim/recommender/cluster_state_provider/FileClusterStateProvider.py
vasim/recommender/cluster_state_provider/PredictiveFileClusterStateProvider.py
vasim/recommender/cluster_state_provider/__init__.py
vasim/recommender/forecasting/TimeSeriesForecaster.py
vasim/recommender/forecasting/__init__.py
vasim/recommender/forecasting/models/__init__.py
vasim/recommender/forecasting/models/oracle.py
vasim/recommender/forecasting/utils/__init__.py
vasim/recommender/forecasting/utils/helpers.py
vasim/simulator/InMemorySimulator.py
vasim/simulator/ParameterTuning.py
vasim/simulator/SimulatedBaseClusterStateProvider.py
vasim/simulator/SimulatedClusterStateProviderFactory.py
vasim/simulator/SimulatedInMemoryClusterStateProvider.py
vasim/simulator/SimulatedInMemoryPredictiveClusterStateProvider.py
vasim/simulator/SimulatedInfraScaler.py
vasim/simulator/__init__.py
vasim/simulator/analysis/ParetoFront2D.py
vasim/simulator/analysis/ParetoFrontier.py
vasim/simulator/analysis/__init__.py
vasim/simulator/analysis/pareto_visualization.py
vasim/simulator/analysis/plot_utils.py
vasim-0.1.4.dist-info/LICENSE
vasim-0.1.4.dist-info/METADATA
vasim-0.1.4.dist-info/WHEEL
vasim-0.1.4.dist-info/top_level.txt
vasim-0.1.4.dist-info/RECORD
