Metadata-Version: 2.1
Name: vasim
Version: 0.1.4
Summary: Vertical Autoscaler Simulator Toolkit
Maintainer-email: VASim Maintainers <vasim-maintainers@service.microsoft.com>
License: MIT License
Project-URL: Repository, https://github.com/microsoft/vasim
Project-URL: Issues, https://github.com/microsoft/vasim/issues
Keywords: data analysis,visualization
Classifier: Intended Audience :: Developers
Classifier: Intended Audience :: System Administrators
Classifier: Intended Audience :: Science/Research
Classifier: License :: OSI Approved :: MIT License
Classifier: Operating System :: OS Independent
Classifier: Programming Language :: Python :: 3
Classifier: Programming Language :: Python :: 3.10
Classifier: Topic :: Scientific/Engineering :: Information Analysis
Classifier: Topic :: Scientific/Engineering :: Visualization
Classifier: Topic :: System
Requires-Python: >=3.9
License-File: LICENSE
Requires-Dist: cvxpy~=1.5.2
Requires-Dist: jsonargparse~=4.21.0
Requires-Dist: matplotlib~=3.7.1
Requires-Dist: numpy~=1.24.2
Requires-Dist: pandas~=1.5.3
Requires-Dist: plotnine~=0.12.2
Requires-Dist: python-dateutil~=2.8.2
Requires-Dist: requests~=2.32.0
Requires-Dist: sktime~=0.16.1
Provides-Extra: dev
Requires-Dist: autopep8; extra == "dev"
Requires-Dist: flake8; extra == "dev"
Requires-Dist: pylint; extra == "dev"
Requires-Dist: black; extra == "dev"
Requires-Dist: isort; extra == "dev"
Requires-Dist: pydocstringformatter; extra == "dev"
Requires-Dist: pytest; extra == "dev"
Requires-Dist: pytest-cov; extra == "dev"
Requires-Dist: pytest-xdist; extra == "dev"
Requires-Dist: coverage; extra == "dev"
Requires-Dist: pre-commit; extra == "dev"
